{
  "version": "0.1.0",
  "released_at": "2026-06-27T19:13:47Z",
  "min_supported_version": "0.1.0",
  "github_repo": "akselbruun29-sys/CoinWallet",
  "signer_fingerprint": null,
  "signing_keys_url": "/releases/signing-keys.example.json",
  "release_notes": "Windows NSIS installer. Run setup wizard to install CoinWallet.",
  "platforms": {
    "windows": {
      "url": "https://github.com/akselbruun29-sys/CoinWallet/releases/download/v0.1.0/coinwallet-windows-x64-setup.exe",
      "sha256": "9b97e0cc78149780e9af58f7d49b62b7fa43b75f879312fb1f0486d72e0644e5",
      "signature": null,
      "signature_status": "unsigned",
      "signer_fingerprint": null,
      "available": true
    },
    "macos": {
      "url": "/releases/coinwallet-macos.dmg",
      "sha256": null,
      "signature": null,
      "signature_status": "unsigned",
      "signer_fingerprint": null,
      "available": false
    }
  }
}
